raphson_music_headless/__init__.py
raphson_music_headless/__main__.py
raphson_music_headless/client.py
raphson_music_headless/config.py
raphson_music_headless/downloader.py
raphson_music_headless/headless_typing.py
raphson_music_headless/index.html
raphson_music_headless/player.py
raphson_music_headless/py.typed
raphson_music_headless/server.py
raphson_music_headless/backend/__init__.py
raphson_music_headless/backend/mpv_backend.py
raphson_music_headless/backend/vlc_backend.py
raphson_music_headless-1.5.0.dist-info/METADATA
raphson_music_headless-1.5.0.dist-info/WHEEL
raphson_music_headless-1.5.0.dist-info/entry_points.txt
raphson_music_headless-1.5.0.dist-info/RECORD
