Metadata-Version: 2.4
Name: raphson_music_headless
Version: 1.5.0
Summary: Headless music player server for the Raphson music player
Project-URL: Homepage, https://codeberg.org/raphson/music-headless
Project-URL: Issues, https://codeberg.org/raphson/music-headless/issues
Author-email: Robin Slot <robin@rslot.nl>
Classifier: Development Status :: 5 - Production/Stable
Classifier: Environment :: No Input/Output (Daemon)
Classifier: Framework :: AsyncIO
Classifier: Intended Audience :: System Administrators
Classifier: License :: OSI Approved :: GNU General Public License v3 (GPLv3)
Classifier: Natural Language :: English
Classifier: Operating System :: OS Independent
Classifier: Programming Language :: Python :: 3
Classifier: Topic :: Multimedia :: Sound/Audio :: Players
Classifier: Typing :: Typed
Requires-Python: >=3.11
Requires-Dist: aiohttp~=3.0
Requires-Dist: raphson-mp~=2.12.0
Requires-Dist: typing-extensions~=4.0
Provides-Extra: dev
Requires-Dist: build; extra == 'dev'
Requires-Dist: python-mpv<2.0,>=1.0.8; extra == 'dev'
Requires-Dist: python-vlc~=3.0; extra == 'dev'
Requires-Dist: twine; extra == 'dev'
Provides-Extra: mpv
Requires-Dist: python-mpv<2.0,>=1.0.8; extra == 'mpv'
Provides-Extra: vlc
Requires-Dist: python-vlc~=3.0; extra == 'vlc'
